sortipy/__init__.py
sortipy/test.py
sortipy/algorithms/__init__.py
sortipy/algorithms/bitonic_sort.py
sortipy/algorithms/bubble_sort.py
sortipy/algorithms/bucket_sort.py
sortipy/algorithms/cocktail_shaker_sort.py
sortipy/algorithms/counting_sort.py
sortipy/algorithms/flash_sort.py
sortipy/algorithms/gnome_sort.py
sortipy/algorithms/heap_sort.py
sortipy/algorithms/insertion_sort.py
sortipy/algorithms/merge_sort.py
sortipy/algorithms/pancake_sort.py
sortipy/algorithms/pigeonhole_sort.py
sortipy/algorithms/quick_sort.py
sortipy/algorithms/radix_sort.py
sortipy/algorithms/selection_sort.py
sortipy/algorithms/shell_sort.py
sortipy/algorithms/tim_sort.py
sortifly-0.1.dist-info/METADATA
sortifly-0.1.dist-info/WHEEL
sortifly-0.1.dist-info/license
sortifly-0.1.dist-info/top_level.txt
sortifly-0.1.dist-info/RECORD
