Metadata-Version: 2.1
Name: sortifly
Version: 0.1
Summary: A collection of sorting algorithms in Python
Home-page: https://github.com/sidge4real/sortipy
Author: Lukas Van der Spiegel
Author-email: 
Classifier: Programming Language :: Python :: 3
Classifier: License :: OSI Approved :: MIT License
Classifier: Operating System :: OS Independent
Requires-Python: >=3.6
License-File: license
Requires-Dist: matplotlib
Requires-Dist: numpy
